mmanalysis/__init__.py
mmanalysis/config.py
mmanalysis/main_analysis.py
mmanalysis/mmanalysis.py
mmanalysis/cli/__init__.py
mmanalysis/cli/mmanalysis_cli.py
mmanalysis/core/__init__.py
mmanalysis/core/fits.py
mmanalysis/core/settings.py
mmanalysis/data/Example_Al2O3_calib_10keV_6p25_2p0_35p0_10s.tif
mmanalysis/data/alumina.D
mmanalysis/data/default_calibration.poni
mmanalysis/data/ito_calibrant.D
mmanalysis/gui/__init__.py
mmanalysis/gui/mma_gui.py
mmanalysis/io/__init__.py
mmanalysis/io/importing.py
mmanalysis/io/pyFAICalibration.py
mmanalysis/visualization/__init__.py
mmanalysis/visualization/plots.py
mmanalysis-1.0.2.dist-info/METADATA
mmanalysis-1.0.2.dist-info/WHEEL
mmanalysis-1.0.2.dist-info/entry_points.txt
mmanalysis-1.0.2.dist-info/top_level.txt
mmanalysis-1.0.2.dist-info/RECORD
