Metadata-Version: 2.4
Name: mmanalysis
Version: 1.0.2
Summary: MultiModalAnalysis is a package to easily postprocess GIWAXS data.
Home-page: https://github.com/sutterfellalab/MultiModalAnalysis
Author: attr:mmanalysis.__author__
Author-email: TimKodalle@lbl.gov
License: Apache-2.0
Classifier: Programming Language :: Python :: 3
Classifier: License :: OSI Approved :: Apache Software License
Classifier: Operating System :: OS Independent
Classifier: Topic :: Software Development
Classifier: Topic :: Scientific/Engineering
Requires-Python: >=3.6
Requires-Dist: numpy
Requires-Dist: scipy
Requires-Dist: pandas
Requires-Dist: dill
Requires-Dist: matplotlib
Requires-Dist: tk
Requires-Dist: lmfit
Requires-Dist: bokeh
Requires-Dist: tqdm
Requires-Dist: h5py
Requires-Dist: pyFAI
Requires-Dist: pyqt5
Requires-Dist: pyside6
Requires-Dist: pyqt6
Requires-Dist: pyopencl
Dynamic: requires-dist
